Workbook

Sheet Summary
A1: Particulars | B1: Current Value | C1: Total Cost
A2: Stocks | B2: =Stocks!$J$16 | C2: =Stocks!$F$16
A3: ETFs | B3: =ETFs!$J$7 | C3: =ETFs!$F$7
A4: Mutual Funds | B4: ='Mutual Funds'!$G$8 | C4: ='Mutual Funds'!$E$8
A5: Total | B5: =SUM(B2:B4) | C5: =SUM(C2:C4)
A7: % Upside/Downside | B7: =(B5-C5)/C5

Sheet Stocks
A1: Sr No. | B1: Name of Stock | C1: Date of purchase | D1: Quantity Purchased | E1: Purchase Price | F1: Total Value | G1: Charges paid | H1: Total Cost | I1: LTP | J1: Current Value of Investment | K1: Date of Sale | L1: Quantity of sale | M1: Sale Price | N1: Charges paid | O1: Total Value of Sale | P1: Profit/Loss
A2: 1 | B2: HDFC BANK | F2: =D2*E2 | H2: =F2+G2 | I2: 692.8 | J2: =(D2-L2)*I2 | O2: =(L2*M2)-N2 | P2: =O2-(L2*E2)
A3: =A2+1 | B3: TCS | F3: =D3*E3 | H3: =F3+G3 | I3: 2530 | J3: =(D3-L3)*I3 | O3: =(L3*M3)-N3 | P3: =O3-(L3*E3)
A4: =A3+1 | B4: RELIANCE | F4: =D4*E4 | H4: =F4+G4 | I4: 1190 | J4: =(D4-L4)*I4 | O4: =(L4*M4)-N4 | P4: =O4-(L4*E4)
A5: =A4+1 | B5: VARUN BEVERAGES | F5: =D5*E5 | H5: =F5+G5 | I5: 395.1 | J5: =(D5-L5)*I5 | O5: =(L5*M5)-N5 | P5: =O5-(L5*E5)
A6: =A5+1 | F6: =D6*E6 | H6: =F6+G6 | J6: =(D6-L6)*I6 | O6: =(L6*M6)-N6 | P6: =O6-(L6*E6)
A7: =A6+1 | F7: =D7*E7 | H7: =F7+G7 | J7: =(D7-L7)*I7 | O7: =(L7*M7)-N7 | P7: =O7-(L7*E7)
A8: =A7+1 | F8: =D8*E8 | H8: =F8+G8 | J8: =(D8-L8)*I8 | O8: =(L8*M8)-N8 | P8: =O8-(L8*E8)
A9: =A8+1 | F9: =D9*E9 | H9: =F9+G9 | J9: =(D9-L9)*I9 | O9: =(L9*M9)-N9 | P9: =O9-(L9*E9)
A10: =A9+1 | F10: =D10*E10 | H10: =F10+G10 | J10: =(D10-L10)*I10 | O10: =(L10*M10)-N10 | P10: =O10-(L10*E10)
A11: =A10+1 | F11: =D11*E11 | H11: =F11+G11 | J11: =(D11-L11)*I11 | O11: =(L11*M11)-N11 | P11: =O11-(L11*E11)
A12: =A11+1 | F12: =D12*E12 | H12: =F12+G12 | J12: =(D12-L12)*I12 | O12: =(L12*M12)-N12 | P12: =O12-(L12*E12)
A13: =A12+1 | F13: =D13*E13 | H13: =F13+G13 | J13: =(D13-L13)*I13 | O13: =(L13*M13)-N13 | P13: =O13-(L13*E13)
A14: =A13+1 | F14: =D14*E14 | H14: =F14+G14 | J14: =(D14-L14)*I14 | O14: =(L14*M14)-N14 | P14: =O14-(L14*E14)
B16: Total | F16: =SUM(F2:F15) | H16: =SUM(H2:H15) | J16: =SUM(J2:J15) | P16: =SUM(P2:P15)
B17: % upside/downside | F17: =(J16-F16)/F16

Sheet ETFs
A1: Sr No. | B1: Name of Stock | C1: Date of purchase | D1: Quantity Purchased | E1: Purchase Price | F1: Total Value | G1: Charges paid | H1: Total Cost | I1: LTP | J1: Current Value of Investment | K1: Date of Sale | L1: Quantity of sale | M1: Sale Price | N1: Charges paid | O1: Total Value of Sale | P1: Profit/Loss
A2: 1 | B2: TATASIL | F2: =D2*E2 | H2: =F2+G2 | I2: 18.69 | J2: =(D2-L2)*I2 | O2: =(L2*M2)-N2 | P2: =O2-(L2*E2)
A3: =A2+1 | B3: TATAGOLD | F3: =D3*E3 | H3: =F3+G3 | I3: 13.63 | J3: =(D3-L3)*I3 | O3: =(L3*M3)-N3 | P3: =O3-(L3*E3)
A4: =A3+1 | B4: NIFTYBEES | F4: =D4*E4 | H4: =F4+G4 | I4: 257.22 | J4: =(D4-L4)*I4 | O4: =(L4*M4)-N4 | P4: =O4-(L4*E4)
A5: =A4+1 | F5: =D5*E5 | H5: =F5+G5 | J5: =(D5-L5)*I5 | O5: =(L5*M5)-N5 | P5: =O5-(L5*E5)
B7: Total | F7: =SUM(F2:F6) | H7: =SUM(H2:H6) | J7: =SUM(J2:J6) | P7: =SUM(P2:P6)
B8: % upside/downside | F8: =(J7-F7)/F7

Sheet Mutual Funds
A1: Sr No. | B1: Name of Stock | C1: Total Units | D1: Average Price | E1: Total Cost | F1: NAV | G1: Current Value of Investment | H1: Profit/Loss | I1: Profit/Loss
A2: 1 | B2: Axis Small Cap Fund | C2: 801.022 | D2: 103.61 | E2: =C2*D2 | F2: 124.67 | G2: =C2*F2 | H2: =G2-E2 | I2: =H2/E2
A3: =A2+1 | B3: Parag Parikh Flexi Cap Fund | C3: 1048.87 | D3: 76.75 | E3: =C3*D3 | F3: 88.9695 | G3: =C3*F3 | H3: =G3-E3 | I3: =H3/E3
A4: =A3+1 | B4: JioBlackRock Flexi Cap | C4: 8231.881 | D4: 10.08 | E4: =C4*D4 | F4: 9.2342 | G4: =C4*F4 | H4: =G4-E4 | I4: =H4/E4
A5: =A4+1 | B5: HDFC Mid Cap | E5: =C5*D5 | F5: 213.423 | G5: =C5*F5 | H5: =G5-E5 | I5: =H5/E5
A6: =A5+1 | B6: SBI Contra | E6: =C6*D6 | F6: 387.1125 | G6: =C6*F6 | H6: =G6-E6 | I6: =H6/E6
B8: Total | E8: =SUM(E2:E7) | G8: =SUM(G2:G7) | H8: =SUM(H2:H7)
B9: % upside/downside | E9: =H8/E8
